.gitignore
.pre-commit-config.yaml
CONTRIBUTING.md
LICENSE
README.md
pyproject.toml
setup.cfg
setup.py
.github/PULL_REQUEST_TEMPLATE.md
.github/release-drafter.yml
.github/ISSUE_TEMPLATE/bug.md
.github/ISSUE_TEMPLATE/feature.md
.github/ISSUE_TEMPLATE/work-item.md
.github/workflows/codeql.yaml
.github/workflows/commitlint.yaml
.github/workflows/draft.yaml
.github/workflows/prtitle.yaml
.github/workflows/publish.yaml
.github/workflows/test.yaml
ape_pulsechain/__init__.py
ape_pulsechain/ecosystem.py
ape_pulsechain/py.typed
ape_pulsechain/version.py
ape_pulsechain.egg-info/PKG-INFO
ape_pulsechain.egg-info/SOURCES.txt
ape_pulsechain.egg-info/dependency_links.txt
ape_pulsechain.egg-info/not-zip-safe
ape_pulsechain.egg-info/requires.txt
ape_pulsechain.egg-info/top_level.txt
tests/__init__.py
tests/conftest.py
tests/test_config.py
tests/test_ecosystem.py
tests/test_integration.py
tests/test_provider.py