Metadata-Version: 2.1
Name: ape-pulsechain
Version: 0.1.0
Summary: ape-pulsechain: Ape Ecosystem Plugin for PulseChain
Home-page: https://github.com/ApeWorX/ape-pulsechain
Author: ApeWorX Ltd.
Author-email: admin@apeworx.io
License: Apache-2.0
Keywords: ethereum
Classifier: Development Status :: 5 - Production/Stable
Classifier: Intended Audience :: Developers
Classifier: License :: OSI Approved :: Apache Software License
Classifier: Natural Language :: English
Classifier: Operating System :: MacOS
Classifier: Operating System :: POSIX
Classifier: Programming Language :: Python :: 3
Classifier: Programming Language :: Python :: 3.8
Classifier: Programming Language :: Python :: 3.9
Classifier: Programming Language :: Python :: 3.10
Classifier: Programming Language :: Python :: 3.11
Requires-Python: >=3.8,<4
License-File: LICENSE
Requires-Dist: eth-ape<0.8,>=0.7.6
Requires-Dist: ethpm-types
Provides-Extra: test
Requires-Dist: pytest>=6.0; extra == "test"
Requires-Dist: pytest-xdist; extra == "test"
Requires-Dist: pytest-cov; extra == "test"
Requires-Dist: hypothesis<7.0,>=6.2.0; extra == "test"
Provides-Extra: lint
Requires-Dist: black>=24.2.0; extra == "lint"
Requires-Dist: mypy<2,>=1.8.0; extra == "lint"
Requires-Dist: types-setuptools; extra == "lint"
Requires-Dist: types-requests; extra == "lint"
Requires-Dist: flake8<8,>=7.0.0; extra == "lint"
Requires-Dist: flake8-breakpoint<2,>=1.1.0; extra == "lint"
Requires-Dist: flake8-print<6,>=5.0.0; extra == "lint"
Requires-Dist: isort<6,>=5.10.1; extra == "lint"
Requires-Dist: mdformat>=0.7.17; extra == "lint"
Requires-Dist: mdformat-gfm>=0.3.5; extra == "lint"
Requires-Dist: mdformat-frontmatter>=0.4.1; extra == "lint"
Requires-Dist: mdformat-pyproject>=0.0.1; extra == "lint"
Provides-Extra: release
Requires-Dist: setuptools; extra == "release"
Requires-Dist: wheel; extra == "release"
Requires-Dist: twine; extra == "release"
Provides-Extra: dev
Requires-Dist: pytest>=6.0; extra == "dev"
Requires-Dist: pytest-xdist; extra == "dev"
Requires-Dist: pytest-cov; extra == "dev"
Requires-Dist: hypothesis<7.0,>=6.2.0; extra == "dev"
Requires-Dist: black>=24.2.0; extra == "dev"
Requires-Dist: mypy<2,>=1.8.0; extra == "dev"
Requires-Dist: types-setuptools; extra == "dev"
Requires-Dist: types-requests; extra == "dev"
Requires-Dist: flake8<8,>=7.0.0; extra == "dev"
Requires-Dist: flake8-breakpoint<2,>=1.1.0; extra == "dev"
Requires-Dist: flake8-print<6,>=5.0.0; extra == "dev"
Requires-Dist: isort<6,>=5.10.1; extra == "dev"
Requires-Dist: mdformat>=0.7.17; extra == "dev"
Requires-Dist: mdformat-gfm>=0.3.5; extra == "dev"
Requires-Dist: mdformat-frontmatter>=0.4.1; extra == "dev"
Requires-Dist: mdformat-pyproject>=0.0.1; extra == "dev"
Requires-Dist: setuptools; extra == "dev"
Requires-Dist: wheel; extra == "dev"
Requires-Dist: twine; extra == "dev"
Requires-Dist: commitizen; extra == "dev"
Requires-Dist: pre-commit; extra == "dev"
Requires-Dist: pytest-watch; extra == "dev"
Requires-Dist: IPython; extra == "dev"
Requires-Dist: ipdb; extra == "dev"
